EMenus/EMenus.py
EMenus/__init__.py
EMenus-0.0.82.dist-info/LICENCE.txt
EMenus-0.0.82.dist-info/METADATA
EMenus-0.0.82.dist-info/WHEEL
EMenus-0.0.82.dist-info/top_level.txt
EMenus-0.0.82.dist-info/RECORD
