Metadata-Version: 2.1
Name: EMenus
Version: 0.0.82
Summary: EMenus - fexible menus, encryption and much more!
Home-page: https://github.com/HUSKI3/EMenus
Author: Artur Zaytsev
Author-email: huskielunar@gmail.com
License: MIT
Keywords: menus,easier,Artur Zaytsev,EMenus
Platform: UNKNOWN
Classifier: Development Status :: 3 - Alpha
Classifier: Intended Audience :: Developers
Classifier: Topic :: Software Development :: Build Tools
Classifier: License :: OSI Approved :: MIT License
Classifier: Programming Language :: Python :: 2.7
Classifier: Programming Language :: Python :: 3
Classifier: Programming Language :: Python :: 3.2
Classifier: Programming Language :: Python :: 3.3
Classifier: Programming Language :: Python :: 3.4
